bombfuse/__init__.py
bombfuse-0.3.3.dist-info/LICENSE
bombfuse-0.3.3.dist-info/METADATA
bombfuse-0.3.3.dist-info/WHEEL
bombfuse-0.3.3.dist-info/top_level.txt
bombfuse-0.3.3.dist-info/RECORD
