Metadata-Version: 2.1
Name: bombfuse
Version: 0.3.3
Summary: Specify a timeout with any given function
Home-page: https://github.com/munshigroup/bombfuse
Author: The Munshi Group
Author-email: support@munshigroup.com
License: UNKNOWN
Keywords: timeout timed timer
Platform: UNKNOWN
Classifier: Programming Language :: Python :: 3
Classifier: Programming Language :: Python :: 2.7
Classifier: License :: OSI Approved :: MIT License
Classifier: Operating System :: OS Independent
License-File: LICENSE
Requires-Dist: kthread
